GrandExchange/GrandExchange.py
GrandExchange/__init__.py
GrandExchange-0.1.1.dist-info/LICENSE
GrandExchange-0.1.1.dist-info/METADATA
GrandExchange-0.1.1.dist-info/WHEEL
GrandExchange-0.1.1.dist-info/top_level.txt
GrandExchange-0.1.1.dist-info/RECORD
