Metadata-Version: 2.1
Name: GrandExchange
Version: 0.1.1
Summary: A python wrapper for OSBuddy exchange data.
Home-page: https://github.com/ejedev/GrandExchange
Author: ejedev
Author-email: ev3098@gmail.com
License: GPL-3.0
Download-URL: https://github.com/ejedev/GrandExchange/archive/v0.1.1.tar.gz
Keywords: OSRS,Oldschool,Runescape,Grand,Exchange,OSBuddy
Platform: UNKNOWN
Classifier: Development Status :: 4 - Beta
Classifier: Intended Audience :: Developers
Classifier: Topic :: Software Development :: Build Tools
Classifier: License :: OSI Approved :: GNU General Public License v3 (GPLv3)
Classifier: Programming Language :: Python :: 3.6
Classifier: Programming Language :: Python :: 3.7
Classifier: Programming Language :: Python :: 3.8
Requires-Dist: wheel
Requires-Dist: tabulate
